kubelingo/__init__.py
kubelingo/issue_manager.py
kubelingo/kubelingo.py
kubelingo/question_generator.py
kubelingo/study_session.py
kubelingo/utils.py
kubelingo/validation.py
kubelingo-0.2.3.dist-info/licenses/LICENSE
misc/color_ascii.py
misc/agent/__init__.py
misc/agent/cli.py
misc/agent/conceptual_guard.py
misc/agent/git_manager.py
scripts/backup_performance_yaml.py
scripts/bump_version.py
scripts/question-mangage.py
tests/conftest.py
tests/test_issue_manager.py
tests/test_kubelingo.py
tests/test_performance.py
tests/test_question_generator.py
tests/test_source.py
tests/test_study_session.py
tests/test_utils.py
tests/test_validation.py
kubelingo-0.2.3.dist-info/METADATA
kubelingo-0.2.3.dist-info/WHEEL
kubelingo-0.2.3.dist-info/entry_points.txt
kubelingo-0.2.3.dist-info/top_level.txt
kubelingo-0.2.3.dist-info/RECORD
