Metadata-Version: 2.4
Name: kubelingo
Version: 0.2.3
Summary: CKAD Studying Tool
Author-email: Edward Joseph <aptnative@gmail.com>
License-Expression: MIT
Project-URL: Homepage, https://github.com/josephedward/kubelingo
Classifier: Programming Language :: Python :: 3
Classifier: Operating System :: OS Independent
Requires-Python: >=3.8
License-File: LICENSE
Requires-Dist: boto3>=1.26.0
Requires-Dist: click>=8.0.0
Requires-Dist: colorama>=0.4.4
Requires-Dist: kubernetes>=25.0.0
Requires-Dist: PyYAML>=6.0
Requires-Dist: questionary>=1.10.0
Requires-Dist: python-dotenv>=0.21.0
Provides-Extra: test
Requires-Dist: pytest>=6.0; extra == "test"
Requires-Dist: requests>=2.28.0; extra == "test"
Provides-Extra: llm
Requires-Dist: llm>=0.14.0; extra == "llm"
Requires-Dist: llm-openai>=0.5.0; extra == "llm"
Requires-Dist: llm-gemini>=0.5.0; extra == "llm"
Dynamic: license-file
